{
  "entries": [
    {
      "generated_at_local": "2026-07-12T07:46:25.441852+01:00",
      "generated_at_utc": "2026-07-12T06:46:25.441852+00:00",
      "beaches_count": 45,
      "weather_items": 45,
      "forecast_items": 45,
      "sea_points": 12,
      "source": "github-actions"
    },
    {
      "generated_at_local": "2026-07-12T04:54:49.657578+01:00",
      "generated_at_utc": "2026-07-12T03:54:49.657578+00:00",
      "beaches_count": 45,
      "weather_items": 45,
      "forecast_items": 45,
      "sea_points": 12,
      "source": "github-actions"
    },
    {
      "generated_at_local": "2026-07-11T22:03:59.838247+01:00",
      "generated_at_utc": "2026-07-11T21:03:59.838247+00:00",
      "beaches_count": 45,
      "weather_items": 45,
      "forecast_items": 45,
      "sea_points": 12,
      "source": "github-actions"
    },
    {
      "generated_at_local": "2026-07-11T18:14:42.149986+01:00",
      "generated_at_utc": "2026-07-11T17:14:42.149986+00:00",
      "beaches_count": 45,
      "weather_items": 45,
      "forecast_items": 45,
      "sea_points": 12,
      "source": "github-actions"
    },
    {
      "generated_at_local": "2026-07-11T14:52:15.456515+01:00",
      "generated_at_utc": "2026-07-11T13:52:15.456515+00:00",
      "beaches_count": 45,
      "weather_items": 45,
      "forecast_items": 45,
      "sea_points": 12,
      "source": "github-actions"
    },
    {
      "generated_at_local": "2026-07-11T10:47:55.834191+01:00",
      "generated_at_utc": "2026-07-11T09:47:55.834191+00:00",
      "beaches_count": 45,
      "weather_items": 45,
      "forecast_items": 45,
      "sea_points": 12,
      "source": "github-actions"
    },
    {
      "generated_at_local": "2026-07-11T07:25:33.074970+01:00",
      "generated_at_utc": "2026-07-11T06:25:33.074970+00:00",
      "beaches_count": 45,
      "weather_items": 45,
      "forecast_items": 45,
      "sea_points": 12,
      "source": "github-actions"
    },
    {
      "generated_at_local": "2026-07-11T04:39:28.844747+01:00",
      "generated_at_utc": "2026-07-11T03:39:28.844747+00:00",
      "beaches_count": 45,
      "weather_items": 45,
      "forecast_items": 45,
      "sea_points": 12,
      "source": "github-actions"
    },
    {
      "generated_at_local": "2026-07-10T22:20:12.154547+01:00",
      "generated_at_utc": "2026-07-10T21:20:12.154547+00:00",
      "beaches_count": 45,
      "weather_items": 45,
      "forecast_items": 45,
      "sea_points": 12,
      "source": "github-actions"
    },
    {
      "generated_at_local": "2026-07-10T19:00:40.552303+01:00",
      "generated_at_utc": "2026-07-10T18:00:40.552303+00:00",
      "beaches_count": 45,
      "weather_items": 45,
      "forecast_items": 45,
      "sea_points": 12,
      "source": "github-actions"
    },
    {
      "generated_at_local": "2026-07-10T15:51:50.525484+01:00",
      "generated_at_utc": "2026-07-10T14:51:50.525484+00:00",
      "beaches_count": 45,
      "weather_items": 45,
      "forecast_items": 45,
      "sea_points": 12,
      "source": "github-actions"
    },
    {
      "generated_at_local": "2026-07-10T12:18:34.264434+01:00",
      "generated_at_utc": "2026-07-10T11:18:34.264434+00:00",
      "beaches_count": 45,
      "weather_items": 45,
      "forecast_items": 45,
      "sea_points": 12,
      "source": "github-actions"
    },
    {
      "generated_at_local": "2026-07-10T08:51:43.004158+01:00",
      "generated_at_utc": "2026-07-10T07:51:43.004158+00:00",
      "beaches_count": 45,
      "weather_items": 45,
      "forecast_items": 45,
      "sea_points": 12,
      "source": "github-actions"
    },
    {
      "generated_at_local": "2026-07-10T05:13:09.316654+01:00",
      "generated_at_utc": "2026-07-10T04:13:09.316654+00:00",
      "beaches_count": 45,
      "weather_items": 45,
      "forecast_items": 45,
      "sea_points": 12,
      "source": "github-actions"
    },
    {
      "generated_at_local": "2026-07-09T22:42:25.630798+01:00",
      "generated_at_utc": "2026-07-09T21:42:25.630798+00:00",
      "beaches_count": 45,
      "weather_items": 45,
      "forecast_items": 45,
      "sea_points": 12,
      "source": "github-actions"
    },
    {
      "generated_at_local": "2026-07-09T19:09:27.627118+01:00",
      "generated_at_utc": "2026-07-09T18:09:27.627118+00:00",
      "beaches_count": 45,
      "weather_items": 45,
      "forecast_items": 45,
      "sea_points": 12,
      "source": "github-actions"
    },
    {
      "generated_at_local": "2026-07-09T16:33:50.300085+01:00",
      "generated_at_utc": "2026-07-09T15:33:50.300085+00:00",
      "beaches_count": 45,
      "weather_items": 45,
      "forecast_items": 45,
      "sea_points": 12,
      "source": "github-actions"
    },
    {
      "generated_at_local": "2026-07-09T12:18:42.765965+01:00",
      "generated_at_utc": "2026-07-09T11:18:42.765965+00:00",
      "beaches_count": 45,
      "weather_items": 45,
      "forecast_items": 45,
      "sea_points": 12,
      "source": "github-actions"
    },
    {
      "generated_at_local": "2026-07-09T08:54:55.183087+01:00",
      "generated_at_utc": "2026-07-09T07:54:55.183087+00:00",
      "beaches_count": 45,
      "weather_items": 45,
      "forecast_items": 45,
      "sea_points": 12,
      "source": "github-actions"
    },
    {
      "generated_at_local": "2026-07-09T05:12:46.288016+01:00",
      "generated_at_utc": "2026-07-09T04:12:46.288016+00:00",
      "beaches_count": 45,
      "weather_items": 45,
      "forecast_items": 45,
      "sea_points": 12,
      "source": "github-actions"
    }
  ]
}